__init__.py
livecoinwatch.py
LiveCoinWatch-1.0.0.dist-info/LICENSE
LiveCoinWatch-1.0.0.dist-info/METADATA
LiveCoinWatch-1.0.0.dist-info/WHEEL
LiveCoinWatch-1.0.0.dist-info/top_level.txt
LiveCoinWatch-1.0.0.dist-info/RECORD
