Metadata-Version: 2.1
Name: LiveCoinWatch
Version: 1.0.0
Summary: Interface in Python for the Live Coin Watch API
Author: Luke Jones
Project-URL: Homepage, https://github.com/MathematicusLucian/LiveCoinWatch
Project-URL: Issues, https://github.com/MathematicusLucian/LiveCoinWatch/issues
Classifier: Programming Language :: Python :: 3
Classifier: License :: OSI Approved :: MIT License
Classifier: Operating System :: OS Independent
Requires-Python: >=3.8
License-File: LICENSE
